{"GiantSpider": "http://tvtropes.org/pmwiki/pmwiki.php/Main/GiantSpider", "CobwebJungle": "http://tvtropes.org/pmwiki/pmwiki.php/Main/CobwebJungle", "ConnectTheDeaths": "http://tvtropes.org/pmwiki/pmwiki.php/Main/ConnectTheDeaths", "TheEndOfTheWorldAsWeKnowIt": "http://tvtropes.org/pmwiki/pmwiki.php/Main/TheEndOfTheWorldAsWeKnowIt", "EvilOverlooker": "http://tvtropes.org/pmwiki/pmwiki.php/Main/EvilOverlooker", "InfernalRetaliation": "http://tvtropes.org/pmwiki/pmwiki.php/Main/InfernalRetaliation", "KidnappingBirdOfPrey": "http://tvtropes.org/pmwiki/pmwiki.php/Main/KidnappingBirdOfPrey", "OrificeEvacuation": "http://tvtropes.org/pmwiki/pmwiki.php/Main/OrificeEvacuation", "SpidersAreScary": "http://tvtropes.org/pmwiki/pmwiki.php/Main/SpidersAreScary"}